pymzm/__init__.py
pymzm/constant.py
pymzm/constraint.py
pymzm/exceptions.py
pymzm/expression.py
pymzm/misc.py
pymzm/model.py
pymzm/variable.py
pymzm-0.0.1.dist-info/LICENSE
pymzm-0.0.1.dist-info/METADATA
pymzm-0.0.1.dist-info/WHEEL
pymzm-0.0.1.dist-info/top_level.txt
pymzm-0.0.1.dist-info/RECORD
