Metadata-Version: 2.1
Name: pymzm
Version: 0.0.1
Summary: Create pure Minizinc .mzn files from Python using python-minizinc-maker library.
Author-email: Ahmad Othman <ahoth19@student.sdu.dk>
Project-URL: Homepage, https://github.com/Arthod/python-minizinc-maker
Project-URL: Bug Tracker, https://github.com/Arthod/python-minizinc-maker/issues
Classifier: Programming Language :: Python :: 3
Classifier: License :: OSI Approved :: MIT License
Classifier: Operating System :: OS Independent
Requires-Python: >=3.8.0
License-File: LICENSE
